offsb/__init__.py
offsb/_version.py
offsb/op/__init__.py
offsb/op/_version.py
offsb/op/chemper.py
offsb/op/geometry.py
offsb/op/openforcefield.py
offsb/op/openmm.py
offsb/qcarchive/__init__.py
offsb/qcarchive/_version.py
offsb/qcarchive/qca_comparisons.py
offsb/qcarchive/qcatree.py
offsb/rdutil/__init__.py
offsb/rdutil/_version.py
offsb/rdutil/mol.py
offsb/search/__init__.py
offsb/search/_version.py
offsb/search/smiles.py
offsb/tools/__init__.py
offsb/tools/_version.py
offsb/tools/const.py
offsb/tools/util.py
offsb/ui/__init__.py
offsb/ui/qcasb.py
offsb/ui/qca/__init__.py
offsb/ui/qca/download.py
offsb/ui/qca/energy-per-molecule.py
offsb/ui/qca/errors.py
offsb/ui/qca/ff-label.py
offsb/ui/qca/list.py
offsb/ui/qca/measure.py
offsb/ui/qca/run-optimization.py
offsb/ui/qca/submit-optimizations.py
offsb/ui/qca/torsiondrive.py
offsb/ui/smiles/__init__.py
offsb/ui/smiles/generate_cmiles_attributes.py
offsb/ui/smiles/load.py
tests/__init__.py
treedi/__init__.py
treedi/_version.py
treedi/node.py
treedi/tree.py
openff_spellbook-0.0.8.dist-info/LICENSE
openff_spellbook-0.0.8.dist-info/METADATA
openff_spellbook-0.0.8.dist-info/WHEEL
openff_spellbook-0.0.8.dist-info/top_level.txt
openff_spellbook-0.0.8.dist-info/RECORD
