Metadata-Version: 2.1
Name: openff-spellbook
Version: 0.0.8
Summary: Handy functionality for working with OpenFF data
Home-page: https://github.com/mobleylab/openff-spellbook
Author: Trevor Gokey
Author-email: tgokey@uci.edu
License: MIT
Keywords: openff-spellbook
Platform: UNKNOWN
Classifier: Programming Language :: Python :: 3.6
Classifier: Programming Language :: Python :: 3.7
Classifier: License :: OSI Approved :: MIT License
Classifier: Operating System :: OS Independent
Requires-Python: >=3.6
